LICENSE
README.md
setup.py
qhsdk/__init__.py
qhsdk.egg-info/PKG-INFO
qhsdk.egg-info/SOURCES.txt
qhsdk.egg-info/dependency_links.txt
qhsdk.egg-info/requires.txt
qhsdk.egg-info/top_level.txt
qhsdk/pro/__init__.py
qhsdk/pro/client.py
qhsdk/pro/cons.py
qhsdk/pro/data_pro.py
qhsdk/qhkc/__init__.py
qhsdk/qhkc/test.py
qhsdk/utils/__init__.py
qhsdk/utils/token_process.py