Metadata-Version: 2.1
Name: qhsdk
Version: 0.1.11
Summary: A Python SDK for www.qhkch.com!
Home-page: https://github.com/jindaxiang/qhsdk
Author: qhkch
Author-email: jindaxiang@163.com
License: MIT
Keywords: futures finance sdk
Classifier: Programming Language :: Python :: 3
Classifier: License :: OSI Approved :: MIT License
Classifier: Operating System :: OS Independent
Requires-Python: >=3.7
License-File: LICENSE
